tax_calculator/AbstractTaxOutput.py
tax_calculator/IMoney.py
tax_calculator/ITaxCalculator.py
tax_calculator/ITaxContext.py
tax_calculator/__init__.py
tax_calculator/generics.py
tax_calculator/main.py
tax_calculator/version.py
tax_calculator/calculators/CodiceAteco.py
tax_calculator/calculators/RegimeForfettarioTaxCalculator.py
tax_calculator/calculators/RegimeForfettarioTaxContext.py
tax_calculator/calculators/StandardTaxOutput.py
tax_calculator/calculators/__init__.py
tax_calculator/encoders/__init__.py
tax_calculator/encoders/encoders.py
tax_calculator/tests/__init__.py
tax_calculator/tests/test_tax.py
tax_calculator-1.2.4.dist-info/LICENSE.md
tax_calculator-1.2.4.dist-info/METADATA
tax_calculator-1.2.4.dist-info/WHEEL
tax_calculator-1.2.4.dist-info/entry_points.txt
tax_calculator-1.2.4.dist-info/top_level.txt
tax_calculator-1.2.4.dist-info/RECORD
