Metadata-Version: 2.1
Name: tax-calculator
Version: 1.2.4
Summary: Allows you to compute taxes
Home-page: https://github.com/Koldar/tax-calculator
Author: Massimo Bono
Author-email: massimobono1@gmail.com
License: MIT
Keywords: tax
Platform: UNKNOWN
Classifier: Topic :: Utilities
Classifier: License :: OSI Approved :: MIT License
Requires-Python: >=3.6
License-File: LICENSE.md
License-File: README.md
License-File: requirements.txt
License-File: setup.py
License-File: tox.ini
Requires-Dist: arrow (>=1.1.1)
Requires-Dist: beautifulsoup4 (>=4.9.3)
Requires-Dist: python-dateutil (>=2.8.2)
Requires-Dist: requests (>=2.26.0)
Requires-Dist: soupsieve (>=2.2.1)
Requires-Dist: stringcase (>=1.2.0)
Requires-Dist: urllib3 (>=1.26.6)
Requires-Dist: semantic-version (>=2.8.5)
